tree2tabular/__init__.py
tree2tabular/__pycache__/__init__.cpython-38.pyc
tree2tabular/src/__init__.py
tree2tabular/src/srcmain.py
tree2tabular/src/__pycache__/__init__.cpython-38.pyc
tree2tabular/src/__pycache__/srcmain.cpython-38.pyc
tree2tabular-0.1.3.dist-info/METADATA
tree2tabular-0.1.3.dist-info/WHEEL
tree2tabular-0.1.3.dist-info/top_level.txt
tree2tabular-0.1.3.dist-info/RECORD
